0x_middlewares-1.0.0-py3.7-nspkg.pth
zero_ex/middlewares/__init__.py
zero_ex/middlewares/local_message_signer.py
zero_ex/middlewares/py.typed
0x_middlewares-1.0.0.dist-info/METADATA
0x_middlewares-1.0.0.dist-info/WHEEL
0x_middlewares-1.0.0.dist-info/namespace_packages.txt
0x_middlewares-1.0.0.dist-info/top_level.txt
0x_middlewares-1.0.0.dist-info/RECORD
