Metadata-Version: 2.1
Name: 0x-middlewares
Version: 1.0.0
Summary: Web3 middlewares for 0x applications
Home-page: https://github.com/0xproject/0x-monorepo/tree/development/python-packages/middlewares
Author: Michael Huang
Author-email: michaelhly@users.noreply.github.com
License: Apache 2.0
Keywords: ethereum cryptocurrency 0x decentralized blockchain dex exchange
Platform: UNKNOWN
Classifier: Development Status :: 2 - Pre-Alpha
Classifier: Intended Audience :: Developers
Classifier: Intended Audience :: Financial and Insurance Industry
Classifier: License :: OSI Approved :: Apache Software License
Classifier: Natural Language :: English
Classifier: Operating System :: OS Independent
Classifier: Programming Language :: Python
Classifier: Programming Language :: Python :: 3 :: Only
Classifier: Programming Language :: Python :: 3.6
Classifier: Programming Language :: Python :: 3.7
Classifier: Topic :: Internet :: WWW/HTTP
Classifier: Topic :: Office/Business :: Financial
Classifier: Topic :: Other/Nonlisted Topic
Classifier: Topic :: Security :: Cryptography
Classifier: Topic :: Software Development :: Libraries
Classifier: Topic :: Utilities
Requires-Python: >=3.6, <4
Requires-Dist: eth-account
Requires-Dist: eth-keys
Requires-Dist: hexbytes
Requires-Dist: mypy-extensions
Provides-Extra: dev
Requires-Dist: 0x-contract-addresses ; extra == 'dev'
Requires-Dist: 0x-contract-wrappers ; extra == 'dev'
Requires-Dist: 0x-order-utils ; extra == 'dev'
Requires-Dist: web3 ; extra == 'dev'
Requires-Dist: bandit ; extra == 'dev'
Requires-Dist: black ; extra == 'dev'
Requires-Dist: coverage ; extra == 'dev'
Requires-Dist: coveralls ; extra == 'dev'
Requires-Dist: eth-utils ; extra == 'dev'
Requires-Dist: mypy ; extra == 'dev'
Requires-Dist: mypy-extensions ; extra == 'dev'
Requires-Dist: pycodestyle ; extra == 'dev'
Requires-Dist: pydocstyle ; extra == 'dev'
Requires-Dist: pylint ; extra == 'dev'
Requires-Dist: pytest ; extra == 'dev'
Requires-Dist: sphinx ; extra == 'dev'
Requires-Dist: sphinx-autodoc-typehints ; extra == 'dev'
Requires-Dist: tox ; extra == 'dev'
Requires-Dist: twine ; extra == 'dev'
